Traffic Light Controller/TrafficLite.v

// removed clock
module TrafficLite(EWCar, NSCar, EWLite, NSLite);

input EWCar, NSCar;
output EWLite, NSLite;

reg state;
initial state = 0; // set initial state

// following two assignments set the output, which is based only on the state variable.
assign NSLite = ~state; // NSLite on if state = 0
assign EWLite = state; // EWLite on if state = 1

always @(*) // all state updates on a positive

    case(state)
        0: state = EWCar; // change state only if EWCAR
        1: state = NSCar; // change state only if NSCar
    endcase

endmodule

Traffic Light Controller/TrafficLite_tb.v
`timescale 1ps/1ps
`include "TrafficLite.v"

module TrafficLite_tb;

// variables
reg EWCar;
reg NSCar;

/*
could represent physical wires, must be continuously driven
by something, and cannot store a value. Hence, they are assigned values
using continous assignment statements.
*/
wire EWLite;
wire NSLite;

// The TrafficLite function
TrafficLite uut(
    EWCar,
    NSCar,
    EWLite,
    NSLite
);

    initial begin
        $dumpfile("TrafficLite_tb.vcd");
        $dumpvars(0, TrafficLite_tb);

        EWCar = 0; NSCar = 1;
        #10;

        NSCar = 0; EWCar = 1;
        #10;

        EWCar = 0; NSCar = 1;
        #10;

        NSCar = 0; EWCar = 1;
        #10;



        EWCar = 0; NSCar = 1;
        #10;

        NSCar = 0; EWCar = 1;
        #10;

        EWCar = 0; NSCar = 1;
        #10;

        NSCar = 0; EWCar = 1;
        #10;


    end
endmodule

Traffic Light Controller/TrafficLite_tb.vcd
$date
	Sat Oct 15 02:17:24 2022
$end
$version
	Icarus Verilog
$end
$timescale
	1ps
$end
$scope module TrafficLite_tb $end
$var wire 1 ! NSLite $end
$var wire 1 " EWLite $end
$var reg 1 # EWCar $end
$var reg 1 $ NSCar $end
$scope module uut $end
$var wire 1 # EWCar $end
$var wire 1 " EWLite $end
$var wire 1 $ NSCar $end
$var wire 1 ! NSLite $end
$var reg 1 % state $end
$upscope $end
$upscope $end
$enddefinitions $end
$comment Show the parameter values. $end
$dumpall
$end
#0
$dumpvars
0%
1$
0#
0"
1!
$end
#10
0!
1"
1%
1#
0$
#20
1$
0#
#30
1!
0"
0%
1#
0$
#40
1$
0#
#50
0!
1"
1%
1#
0$
#60
1$
0#
#70
1!
0"
0%
1#
0$
